docums_autorefs/plugin.py
docums_autorefs/references.py
docums_autorefs-0.3.1.dist-info/entry_points.txt
docums_autorefs-0.3.1.dist-info/LICENSE
docums_autorefs-0.3.1.dist-info/METADATA
docums_autorefs-0.3.1.dist-info/WHEEL
docums_autorefs-0.3.1.dist-info/RECORD
