Metadata-Version: 2.1
Name: docums-autorefs
Version: 0.3.1
Summary: Automatically link across pages in Docums.
Home-page: https://github.com/documstrings/autorefs
License: ISC
Keywords: docums,docums-plugin,docstrings,autodoc
Author: NKDuy
Author-email: kn145660@gmail.com
Requires-Python: >=3.6.2,<4.0.0
Classifier: License :: OSI Approved
Classifier: Programming Language :: Python :: 3
Classifier: Programming Language :: Python :: 3.7
Classifier: Programming Language :: Python :: 3.8
Classifier: Programming Language :: Python :: 3.9
Classifier: Programming Language :: Python :: 3.10
Classifier: Programming Language :: Python :: 3.11
Requires-Dist: Markdown (>=3.3,<4.0)
Requires-Dist: docums (>=1.1.0,<2.0.0)
Project-URL: Repository, https://github.com/documstrings/autorefs
